{"cameraMode":{"drawMode":0,"name":"Shaded","section":"Shading Mode"},"sceneLighting":true,"audioPlay":false,"sceneViewState":{"m_AlwaysRefresh":false,"showFog":true,"showSkybox":true,"showFlares":true,"showImageEffects":true,"showParticleSystems":true,"showVisualEffectGraphs":true,"m_FxEnabled":true},"in2DMode":false,"pivot":{"x":286.7392578125,"y":-148.21829223632813,"z":457.9169616699219},"rotation":{"x":-0.03584643080830574,"y":-0.907274067401886,"z":0.4115021824836731,"w":-0.07903505116701126},"size":202.64401245117188,"orthographic":false}